twobyfour/__init__.py
twobyfour/operators.py
twobyfour/rotation_conversions.py
twobyfour/_cpu/__init__.py
twobyfour/_cpu/_cpu_operations.py
twobyfour/_cuda/__init__.py
twobyfour/_cuda/_cuda_kernels.py
twobyfour/_cuda/_cuda_operations.py
twobyfour-1.0.3.dist-info/METADATA
twobyfour-1.0.3.dist-info/WHEEL
twobyfour-1.0.3.dist-info/licenses/LICENSE
twobyfour-1.0.3.dist-info/RECORD
